icoapi/api.py
icoapi/config/dataspace.yaml
icoapi/config/default.env
icoapi/config/metadata.yaml
icoapi/config/sensors.yaml
icoapi/models/__init__.py
icoapi/models/globals.py
icoapi/models/models.py
icoapi/models/trident.py
icoapi/routers/__init__.py
icoapi/routers/cloud_routes.py
icoapi/routers/common.py
icoapi/routers/config_routes.py
icoapi/routers/file_routes.py
icoapi/routers/log_routes.py
icoapi/routers/measurement_routes.py
icoapi/routers/sensor_routes.py
icoapi/routers/sth_routes.py
icoapi/routers/stu_routes.py
icoapi/scripts/__init__.py
icoapi/scripts/config_helper.py
icoapi/scripts/data_handling.py
icoapi/scripts/errors.py
icoapi/scripts/file_handling.py
icoapi/scripts/measurement.py
icoapi/scripts/sth_scripts.py
icoapi/scripts/stu_scripts.py
icoapi/utils/__init__.py
icoapi/utils/logging_setup.py
icoapi-0.1.2.dist-info/METADATA
icoapi-0.1.2.dist-info/WHEEL
icoapi-0.1.2.dist-info/entry_points.txt
icoapi-0.1.2.dist-info/RECORD
