Metadata-Version: 2.4
Name: icoapi
Version: 0.1.2
Summary: A REST and WebSocket API for the ICOtronic system using the Python FastAPI library
Keywords: smart-tool,smh,stu,sth,tool-holder
Author: Moritz Breurather
Author-email: breurather@ift.at
Requires-Python: >=3.10,<4
Classifier: Programming Language :: Python :: 3
Classifier: Programming Language :: Python :: 3.10
Classifier: Programming Language :: Python :: 3.11
Classifier: Programming Language :: Python :: 3.12
Classifier: Programming Language :: Python :: 3.13
Classifier: Programming Language :: Python :: 3.14
Provides-Extra: dev
Provides-Extra: test
Requires-Dist: Flake8-pyproject (>=1.2.3) ; extra == "dev"
Requires-Dist: colorlog (>=6.9.0,<7)
Requires-Dist: fastapi (>=0.115.7)
Requires-Dist: httpx (>=0.28.1) ; extra == "test"
Requires-Dist: icoc (>=2,<3)
Requires-Dist: icolyzer (>=1.8.0)
Requires-Dist: mypy ; extra == "dev"
Requires-Dist: orjson (>=3.11.0)
Requires-Dist: pandas (>=2.2.3,<3)
Requires-Dist: pathvalidate (>=3.3.1,<4)
Requires-Dist: pytest ; extra == "test"
Requires-Dist: python-dotenv (>=1.0.1,<2)
Requires-Dist: python-multipart (>=0.0.20)
Requires-Dist: pyyaml (>=6.0.1,<7)
Requires-Dist: types-pyyaml (>=6.0.12.20250915,<7.0.0.0)
Requires-Dist: uvicorn[standard] (>=0.35.0)
